[
{"見出し":"県立近代美術館","電話":"073-436-8690　","ファックス":"073-436-1337 ","住所":"〒640-8137　和歌山市吹上1-4-14","開館時間":"9:30～17:00（入館は16:30まで）","休館日":"休館／月曜（祝日の場合次の平日）","催し名":"コレクション展2017-秋 特集「ＮＡＮＧＡ 俗を去り自ら娯しむ」","区分":"展示","開催日":"?12月17日","場所":"","対象":"","定員":"","費用":"一般510円　学生300円","申込":"","備考":"65歳以上、障害者、高校生以下、外国人留学生などは入場無料"},
{"見出し":"県立近代美術館","電話":"073-436-8690　","ファックス":"073-436-1337 ","住所":"〒640-8137　和歌山市吹上1-4-14","開館時間":"9:30～17:00（入館は16:30まで）","休館日":"休館／月曜（祝日の場合次の平日）","催し名":"特別展「アメリカへ渡った二人 国吉康雄と石垣栄太郎」 ","区分":"展示","開催日":"?12月24日 ","場所":"","対象":"","定員":"","費用":"一般510円　学生301円","申込":"","備考":"65歳以上、障害者、高校生以下、外国人留学生などは入場無料"},
{"見出し":"片男波公園万葉館","電話":"073-446-5553　","ファックス":"073-446-5554","住所":"〒641-0022　 和歌山市和歌浦南3-1700","開館時間":"9:00～17:00 （入館は16:30まで）","休館日":"","催し名":"日曜体験教室「ペーパークラフトかわいいワンちゃんの写真たて」","区分":"イベント","開催日":"12月10日10:30?12:00、13:00?14:30、14:45?16:15","場所":"","対象":"小学生以上（小学生は保護者同伴）","定員":"各8人","費用":"1,500円","申込":"事前申込","備考":"入場無料"},
{"見出し":"片男波公園万葉館","電話":"073-446-5553　","ファックス":"073-446-5554","住所":"〒641-0022　 和歌山市和歌浦南3-1700","開館時間":"9:00～17:00 （入館は16:30まで）","休館日":"","催し名":"日曜体験教室「色紙に干支を描こう！」","区分":"イベント","開催日":"12月17日10:00?12:00、13:00?15:00","場所":"","対象":"小学生以上（小学生は保護者同伴）","定員":"各8人","費用":"1,500円","申込":"事前申込 ","備考":"入場無料"},
{"見出し":"片男波公園万葉館","電話":"073-446-5553　","ファックス":"073-446-5554","住所":"〒641-0022　 和歌山市和歌浦南3-1700","開館時間":"9:00～17:00 （入館は16:30まで）","休館日":"","催し名":"日曜体験教室「季節の寄せ植え」","区分":"イベント","開催日":"12月24日14:00?15:30","場所":"","対象":"小学生以上（小学生は保護者同伴）","定員":"各20人（先着順）","費用":"2,500円","申込":"事前申込 ","備考":"入場無料"},
{"見出し":"県立図書館","電話":"073-436-9500　","ファックス":"073-436-9501","住所":"〒641-0051　和歌山市西高松1-7-38","開館時間":"閲覧室　平日10:00～19:00（土日祝は18:00まで）","休館日":"休館／月曜（祝日の場合は次の平日）、毎月第2木曜","催し名":"南葵音楽文庫ミニレクチャーあかちゃんといっしょに楽しもう～あき～","区分":"イベント","開催日":"12月9日?3月31日毎週土曜日11:00?","場所":"","対象":"","定員":"各回10人（先着順）","費用":"","申込":"","備考":"入場無料"},
{"見出し":"県立図書館","電話":"073-436-9500　","ファックス":"073-436-9501","住所":"〒641-0051　和歌山市西高松1-7-38","開館時間":"閲覧室　平日10:00～19:00（土日祝は18:00まで）","休館日":"休館／月曜（祝日の場合は次の平日）、毎月第2木曜","催し名":"中高生読書まつり（1）ビブリオバトル和歌山大会決勝戦 （2）ビブリオバトル・POPコンクール表彰式","区分":"イベント","開催日":"12月10日12:30?16:15 ","場所":"","対象":"中学生以上","定員":"200人 （先着順）","費用":"","申込":"事前申込（当日参加も可）","備考":"入場無料"},
{"見出し":"県立図書館","電話":"073-436-9500　","ファックス":"073-436-9501","住所":"〒641-0051　和歌山市西高松1-7-38","開館時間":"閲覧室　平日10:00～19:00（土日祝は18:00まで）","休館日":"休館／月曜（祝日の場合は次の平日）、毎月第2木曜","催し名":" ボランティアによる「おはなし会」","区分":"イベント","開催日":"12月16・23日、1月13日14:00?、1月6日11:00?","場所":"","対象":"","定員":"","費用":"","申込":"","備考":"入場無料"},
{"見出し":"県立図書館","電話":"073-436-9500　","ファックス":"073-436-9501","住所":"〒641-0051　和歌山市西高松1-7-38","開館時間":"閲覧室　平日10:00～19:00（土日祝は18:00まで）","休館日":"休館／月曜（祝日の場合は次の平日）、毎月第2木曜","催し名":" エントランスコンサート","区分":"イベント","開催日":"1月5日12:00?12:30 ","場所":"","対象":"","定員":"100人程度（先着順）","費用":"","申込":"","備考":"入場無料"},
{"見出し":"県立自然博物館","電話":"073-483-1777　","ファックス":"073-483-2721","住所":"〒642-0001　海南市船尾370-1","開館時間":"9:30～17:00（入館は16:30まで）","休館日":"休館／月曜（祝日の場合次の平日）","催し名":"サンタが大水槽にやってくる 潜水作業大公開","区分":"イベント","開催日":"12月10・17日11:00?12:00、14:00?15:00 ","場所":"","対象":"","定員":"","費用":"","申込":"","備考":"65歳以上、障害者、高校生以下、外国人留学生などは入場無料"},
{"見出し":"県立自然博物館","電話":"073-483-1777　","ファックス":"073-483-2721","住所":"〒642-0001　海南市船尾370-1","開館時間":"9:30～17:00（入館は16:30まで）","休館日":"休館／月曜（祝日の場合次の平日）","催し名":"裏方探索ツアー（1）","区分":"イベント","開催日":"1月27日10:00?12:00","場所":"","対象":"小学生以上（小学4年生以下は保護者同伴）","定員":"30人（抽選）","費用":"","申込":"11月19日まで","備考":"65歳以上、障害者、高校生以下、外国人留学生などは入場無料"},
{"見出し":"県立紀伊風土記の丘","電話":"073-471-6123　","ファックス":"073-471-6120 ","住所":"〒640-8301　和歌山市岩橋1411","開館時間":"9:00～16:30（入館は16:00まで）","休館日":"休館／月曜（祝日の場合次の平日）","催し名":"ミニ展「ジュニア考古学研究応募作品展」」","区分":"展示","開催日":"12月10日?1月14日","場所":"","対象":"","定員":"","費用":"","申込":"","備考":"65歳以上、障害者、高校生以下、外国人留学生などは入場無料"},
{"見出し":"県立紀伊風土記の丘","電話":"073-471-6123　","ファックス":"073-471-6120 ","住所":"〒640-8301　和歌山市岩橋1411","開館時間":"9:00～16:30（入館は16:00まで）","休館日":"休館／月曜（祝日の場合次の平日）","催し名":"ジュニア考古学研究発表","区分":"イベント","開催日":"12月10日13:30?15:30","場所":"","対象":"小学生以上","定員":"","費用":"","申込":"","備考":"65歳以上、障害者、高校生以下、外国人留学生などは入場無料"},
{"見出し":"県立紀伊風土記の丘","電話":"073-471-6123　","ファックス":"073-471-6120 ","住所":"〒640-8301　和歌山市岩橋1411","開館時間":"9:00～16:30（入館は16:00まで）","休館日":"休館／月曜（祝日の場合次の平日）","催し名":"前山A58号墳の実物大の埴輪を作ろう（3）","区分":"イベント","開催日":"1月13日10:00?16:30","場所":"","対象":"中学生以上","定員":"15人（先着順）","費用":"","申込":"","備考":"65歳以上、障害者、高校生以下、外国人留学生などは入場無料"},
{"見出し":"県立紀伊風土記の丘","電話":"073-471-6123　","ファックス":"073-471-6120 ","住所":"〒640-8301　和歌山市岩橋1411","開館時間":"9:00～16:30（入館は16:00まで）","休館日":"休館／月曜（祝日の場合次の平日）","催し名":"おしえて！！ヤマゲン先生（4）万葉歌と古代の草木花ガイド","区分":"イベント","開催日":"11月26日10:00?12:00","場所":"","対象":"小学生以上","定員":"30人（先着順）","費用":"：(初回)350円","申込":"12月26日13:00?","備考":"65歳以上、障害者、高校生以下、外国人留学生などは入場無料"},
{"見出し":"県植物公園緑花センター","電話":"0736-62-4029　","ファックス":"0736-63-2570 ","住所":"〒649-6211　岩出市東坂本672","開館時間":"9:00～17:00（入館は16:30まで）","休館日":"休館／火曜（祝日の場合次の平日）","催し名":"冬の洋ラン展","区分":"展示","開催日":"12月8?10日","場所":"","対象":"","定員":"","費用":"","申込":"","備考":"入場無料"},
{"見出し":"県植物公園緑花センター","電話":"0736-62-4029　","ファックス":"0736-63-2570 ","住所":"〒649-6211　岩出市東坂本672","開館時間":"9:00～17:00（入館は16:30まで）","休館日":"休館／火曜（祝日の場合次の平日）","催し名":"箏・初春コンサート ","区分":"イベント","開催日":"2017/01/03","場所":"","対象":"","定員":"","費用":"","申込":"","備考":"入場無料"},
{"見出し":"県植物公園緑花センター","電話":"0736-62-4029　","ファックス":"0736-63-2570 ","住所":"〒649-6211　岩出市東坂本672","開館時間":"9:00～17:00（入館は16:30まで）","休館日":"休館／火曜（祝日の場合次の平日）","催し名":"バラの手入れ教室","区分":"イベント","開催日":"2017/01/08","場所":"","対象":"","定員":"36人（先着順）","費用":"300円","申込":"事前申込","備考":"入場無料"},
{"見出し":"県動物愛護センター","電話":"073-489-6500　","ファックス":"073-489-6504 ","住所":"〒640-1251　紀美野町国木原372","開館時間":"10:00～17:00　","休館日":"休館／火曜","催し名":"犬・猫の飼い方講習会及び譲渡会","区分":"","開催日":"（1）12月1･10･24日、1月5･14･28日11:00? （2）12月8日11:00?（3）12月14日13:00?（2）11月10日11:00?（3）11月30日13:00?","場所":"（1）県動物愛護センター（2）東牟婁振興局（新宮市）（3）御坊保健所（御坊市）","対象":"","定員":"","費用":"譲渡を受けるには受講と、犬については狂犬病予防注射代 2,640円が必要です。","申込":"","備考":"入場無料"}
]
